{"total":88,"pageSize":13,"pageCount":7,"data":[{"title":"根据ip获取省份/城市的接口","uid":"b5db695e23294ea81434ac131bd5db81","slug":"根据ip获取省份-城市的接口","date":"2015-10-12T06:47:44.000Z","updated":"2020-03-28T15:50:46.000Z","comments":true,"path":"api/articles/根据ip获取省份-城市的接口.json","cover":null,"text":"###淘宝接口 http://ip.taobao.com/service/getIpInfo.php?ip=119.57.173.141 #####返回结果 &#123; &quot;code&quot;: 0, &quot;data&quot;: &#123; &quot;co...","link":"","photos":[],"count_time":{"symbolsCount":"2k","symbolsTime":"2 mins."},"categories":[{"name":"免费接口","slug":"免费接口","count":1,"path":"api/categories/免费接口.json"}],"tags":[{"name":"API","slug":"API","count":1,"path":"api/tags/API.json"},{"name":"城市","slug":"城市","count":1,"path":"api/tags/城市.json"}],"author":{"name":"新风作浪","slug":"blog-author","avatar":"http://qiniu.niuxtech.cn/avatar.png","link":"/","description":"专注于你能控制的","socials":{"github":"https://github.com/duxinfeng","twitter":"https://twitter.com/iduxinfeng","stackoverflow":"","wechat":"","qq":"","weibo":"","zhihu":"","csdn":"https://blog.csdn.net/duxinfeng2010","juejin":"","customs":{}}}},{"title":"科学上网","uid":"e384082c21cec712db7f9620d92150dc","slug":"科学上网","date":"2015-10-08T05:59:57.000Z","updated":"2020-03-11T12:46:21.000Z","comments":true,"path":"api/articles/科学上网.json","cover":null,"text":"本文不介绍如何翻越长城，只是个人爱好收集的一些免费方法，仅供折腾，不保证百分百成功。 2020.03.11 更新 http:&#x2F;&#x2F;www.googlen.org 2018.10.10 更新 以上方案全部失效，再放几个收藏的镜像网址.镜像只用于简单的搜索查询，请勿...","link":"","photos":[],"count_time":{"symbolsCount":"1.1k","symbolsTime":"1 mins."},"categories":[{"name":"工具","slug":"工具","count":10,"path":"api/categories/工具.json"}],"tags":[{"name":"Google","slug":"Google","count":1,"path":"api/tags/Google.json"}],"author":{"name":"新风作浪","slug":"blog-author","avatar":"http://qiniu.niuxtech.cn/avatar.png","link":"/","description":"专注于你能控制的","socials":{"github":"https://github.com/duxinfeng","twitter":"https://twitter.com/iduxinfeng","stackoverflow":"","wechat":"","qq":"","weibo":"","zhihu":"","csdn":"https://blog.csdn.net/duxinfeng2010","juejin":"","customs":{}}}},{"title":"杂七杂八","uid":"6f1f5344ac40b502498b04742f9397eb","slug":"杂七杂八","date":"2015-09-24T15:20:56.000Z","updated":"2017-04-27T12:16:31.000Z","comments":true,"path":"api/articles/杂七杂八.json","cover":null,"text":"就是有些时候觉得这些话特真实，很有道理，你无以言表，却被人点破。离你很近的就像在描述你自己。于是有了这篇杂七杂八！ 你身处什么样的圈子，你就会遇到什么样的人；你结交了那些朋友，你脾性也会慢慢接近这样的人；你处在什么位置，站在什么高度，决定了你是怎么样的视野；内心多大的格局，你就可...","link":"","photos":[],"count_time":{"symbolsCount":318,"symbolsTime":"1 mins."},"categories":[{"name":"生活","slug":"生活","count":13,"path":"api/categories/生活.json"}],"tags":[{"name":"碎碎念","slug":"碎碎念","count":8,"path":"api/tags/碎碎念.json"}],"author":{"name":"新风作浪","slug":"blog-author","avatar":"http://qiniu.niuxtech.cn/avatar.png","link":"/","description":"专注于你能控制的","socials":{"github":"https://github.com/duxinfeng","twitter":"https://twitter.com/iduxinfeng","stackoverflow":"","wechat":"","qq":"","weibo":"","zhihu":"","csdn":"https://blog.csdn.net/duxinfeng2010","juejin":"","customs":{}}}},{"title":"段子","uid":"7b1d6129af3410552ae41e2877201f0d","slug":"段子","date":"2015-09-24T15:09:18.000Z","updated":"2020-03-11T15:21:10.000Z","comments":true,"path":"api/articles/段子.json","cover":null,"text":"虽然同事叫乎我段子手，但实际还是差的很远，个人也比较喜欢段子，此处作为收集，积累。争取早日进入段子界！ 不是所有的女人都喜欢钱，还有些善良的女人喜欢小动物。例如：宝马，路虎，捷豹，野马，当然还有天猫 转让半瓶雪碧，4月初才买的，喝了才一半，里边还有很多气儿，平时没咋舍得喝，平常喝...","link":"","photos":[],"count_time":{"symbolsCount":509,"symbolsTime":"1 mins."},"categories":[{"name":"生活","slug":"生活","count":13,"path":"api/categories/生活.json"}],"tags":[],"author":{"name":"新风作浪","slug":"blog-author","avatar":"http://qiniu.niuxtech.cn/avatar.png","link":"/","description":"专注于你能控制的","socials":{"github":"https://github.com/duxinfeng","twitter":"https://twitter.com/iduxinfeng","stackoverflow":"","wechat":"","qq":"","weibo":"","zhihu":"","csdn":"https://blog.csdn.net/duxinfeng2010","juejin":"","customs":{}}}},{"title":"个人GitHub Star Repo分类","uid":"d29d68cd8166fec943514684f51fc190","slug":"个人GitHub-Star-Repo分类","date":"2015-09-08T06:09:16.000Z","updated":"2020-03-11T15:21:52.000Z","comments":true,"path":"api/articles/个人GitHub-Star-Repo分类.json","cover":null,"text":"个人GitHub主页Star Repo 分类，方便查找 网络请求库 https://github.com/AFNetworking/AFNetworking https://github.com/Alamofire/AlamofireImage 菜单 https://github...","link":"","photos":[],"count_time":{"symbolsCount":"2k","symbolsTime":"2 mins."},"categories":[{"name":"iOS","slug":"iOS","count":36,"path":"api/categories/iOS.json"}],"tags":[{"name":"源码","slug":"源码","count":2,"path":"api/tags/源码.json"},{"name":"GitHub","slug":"GitHub","count":1,"path":"api/tags/GitHub.json"}],"author":{"name":"新风作浪","slug":"blog-author","avatar":"http://qiniu.niuxtech.cn/avatar.png","link":"/","description":"专注于你能控制的","socials":{"github":"https://github.com/duxinfeng","twitter":"https://twitter.com/iduxinfeng","stackoverflow":"","wechat":"","qq":"","weibo":"","zhihu":"","csdn":"https://blog.csdn.net/duxinfeng2010","juejin":"","customs":{}}}},{"title":"iOS键盘通知","uid":"fe5b28098a33f02f182467f88ab95c02","slug":"iOS键盘通知","date":"2015-08-21T09:32:55.000Z","updated":"2020-03-11T13:09:43.000Z","comments":true,"path":"api/articles/iOS键盘通知.json","cover":[],"text":"iOS系统键盘通知UIKeyboardWillShowNotification &#x2F;&#x2F; 键盘将要出现 UIKeyboardDidShowNotification &#x2F;&#x2F; 键盘已经出现 UIKeyboardWillHideNotification...","link":"","photos":[],"count_time":{"symbolsCount":"1.9k","symbolsTime":"2 mins."},"categories":[{"name":"iOS","slug":"iOS","count":36,"path":"api/categories/iOS.json"}],"tags":[{"name":"键盘","slug":"键盘","count":1,"path":"api/tags/键盘.json"},{"name":"通知","slug":"通知","count":1,"path":"api/tags/通知.json"}],"author":{"name":"新风作浪","slug":"blog-author","avatar":"http://qiniu.niuxtech.cn/avatar.png","link":"/","description":"专注于你能控制的","socials":{"github":"https://github.com/duxinfeng","twitter":"https://twitter.com/iduxinfeng","stackoverflow":"","wechat":"","qq":"","weibo":"","zhihu":"","csdn":"https://blog.csdn.net/duxinfeng2010","juejin":"","customs":{}}}},{"title":"symbolicatecrash 分析iOS Crash文件","uid":"0486f007652796b9b153f0812cb5b6b6","slug":"symbolicatecrash-分析iOS-Crash文件","date":"2015-08-18T05:50:04.000Z","updated":"2020-03-11T12:57:49.000Z","comments":true,"path":"api/articles/symbolicatecrash-分析iOS-Crash文件.json","cover":null,"text":"2018.1.13更新：审核的时候如果是因为崩溃被拒，审核人员会在回复的邮件中附上crash信息(txt文件格式),下载这个文件开始对它进行分析，查看源码崩溃的具体位置。 新建Crash文件夹,把分析工具symbolicatecrash 、崩溃日志crash.txt和.dSYM文...","link":"","photos":[],"count_time":{"symbolsCount":"1.5k","symbolsTime":"1 mins."},"categories":[{"name":"iOS","slug":"iOS","count":36,"path":"api/categories/iOS.json"}],"tags":[{"name":"Crash","slug":"Crash","count":1,"path":"api/tags/Crash.json"}],"author":{"name":"新风作浪","slug":"blog-author","avatar":"http://qiniu.niuxtech.cn/avatar.png","link":"/","description":"专注于你能控制的","socials":{"github":"https://github.com/duxinfeng","twitter":"https://twitter.com/iduxinfeng","stackoverflow":"","wechat":"","qq":"","weibo":"","zhihu":"","csdn":"https://blog.csdn.net/duxinfeng2010","juejin":"","customs":{}}}},{"title":"Xcode 6.4 Build error 没有任何错误issues","uid":"7f5ce444661ab21418e622d405e2364d","slug":"Xcode-6-4-Build-error-没有任何错误issues","date":"2015-07-27T08:21:51.000Z","updated":"2017-04-27T13:02:12.000Z","comments":true,"path":"api/articles/Xcode-6-4-Build-error-没有任何错误issues.json","cover":[],"text":"今天遇到一个很奇怪的问题，我修改了一个变量，然后Xcode一直Build Error ,没有任何提示。尝试Clean、重启XCode、重启Mac都这样，然后在网上找到了一个12年的Blog，尝试了一下解决了。 因为在其他地方也有使用这个变量，我改动这个变量名称后，忘记修改，然后x...","link":"","photos":[],"count_time":{"symbolsCount":218,"symbolsTime":"1 mins."},"categories":[{"name":"工具","slug":"工具","count":10,"path":"api/categories/工具.json"}],"tags":[{"name":"Xcode","slug":"Xcode","count":6,"path":"api/tags/Xcode.json"}],"author":{"name":"新风作浪","slug":"blog-author","avatar":"http://qiniu.niuxtech.cn/avatar.png","link":"/","description":"专注于你能控制的","socials":{"github":"https://github.com/duxinfeng","twitter":"https://twitter.com/iduxinfeng","stackoverflow":"","wechat":"","qq":"","weibo":"","zhihu":"","csdn":"https://blog.csdn.net/duxinfeng2010","juejin":"","customs":{}}}},{"title":"Mantle的使用","uid":"531983b175d1a941a4658cbd55147759","slug":"Mantle的使用","date":"2015-07-25T16:02:12.000Z","updated":"2020-03-11T12:59:55.000Z","comments":true,"path":"api/articles/Mantle的使用.json","cover":null,"text":" 关于Mantle 项目地址：https://github.com/Mantle/Mantle Mantle介绍：Mantle 是Github团队开源出来的一项能够简化Cocoa 和 Cocoa Touch 应用的Model层，避免每次重写-(instancetype)initW...","link":"","photos":[],"count_time":{"symbolsCount":"2.7k","symbolsTime":"2 mins."},"categories":[{"name":"iOS","slug":"iOS","count":36,"path":"api/categories/iOS.json"}],"tags":[{"name":"Mantle","slug":"Mantle","count":2,"path":"api/tags/Mantle.json"}],"author":{"name":"新风作浪","slug":"blog-author","avatar":"http://qiniu.niuxtech.cn/avatar.png","link":"/","description":"专注于你能控制的","socials":{"github":"https://github.com/duxinfeng","twitter":"https://twitter.com/iduxinfeng","stackoverflow":"","wechat":"","qq":"","weibo":"","zhihu":"","csdn":"https://blog.csdn.net/duxinfeng2010","juejin":"","customs":{}}}},{"title":"iOS开源App整理","uid":"b84327d37705f1de265729e915a9e41a","slug":"iOS开源App整理","date":"2015-07-14T05:09:48.000Z","updated":"2017-05-01T15:43:00.000Z","comments":true,"path":"api/articles/iOS开源App整理.json","cover":null,"text":"有时候在逛Weibo、Github的时候看到一些最近开源或者持续更新的iOS项目源码，大部分都已经上线，在这篇Blog里作了整理（排名不分先后，按照发现时间排序）。 开源中国开源中国社区iPhone客户端。 Appstore 下载地址：https://itunes.apple.c...","link":"","photos":[],"count_time":{"symbolsCount":"1.9k","symbolsTime":"2 mins."},"categories":[{"name":"iOS","slug":"iOS","count":36,"path":"api/categories/iOS.json"}],"tags":[{"name":"App","slug":"App","count":1,"path":"api/tags/App.json"},{"name":"源码","slug":"源码","count":2,"path":"api/tags/源码.json"}],"author":{"name":"新风作浪","slug":"blog-author","avatar":"http://qiniu.niuxtech.cn/avatar.png","link":"/","description":"专注于你能控制的","socials":{"github":"https://github.com/duxinfeng","twitter":"https://twitter.com/iduxinfeng","stackoverflow":"","wechat":"","qq":"","weibo":"","zhihu":"","csdn":"https://blog.csdn.net/duxinfeng2010","juejin":"","customs":{}}}},{"title":"RESideMenu源码学习","uid":"fcf55b2f11bf571a37815147521a9750","slug":"RESideMenu源码学习","date":"2015-07-12T14:40:03.000Z","updated":"2020-03-28T12:35:00.000Z","comments":true,"path":"api/articles/RESideMenu源码学习.json","cover":[],"text":"RESideMenu下载地址：https://github.com/romaonthego/RESideMenu RESideMenu 有三个类，RECommonFunctions，RESideMenu，UIViewController+RESideMenu，核心RESideMe...","link":"","photos":[],"count_time":{"symbolsCount":"1.7k","symbolsTime":"2 mins."},"categories":[{"name":"iOS","slug":"iOS","count":36,"path":"api/categories/iOS.json"}],"tags":[{"name":"RESideMenu","slug":"RESideMenu","count":1,"path":"api/tags/RESideMenu.json"}],"author":{"name":"新风作浪","slug":"blog-author","avatar":"http://qiniu.niuxtech.cn/avatar.png","link":"/","description":"专注于你能控制的","socials":{"github":"https://github.com/duxinfeng","twitter":"https://twitter.com/iduxinfeng","stackoverflow":"","wechat":"","qq":"","weibo":"","zhihu":"","csdn":"https://blog.csdn.net/duxinfeng2010","juejin":"","customs":{}}}},{"title":"FMDB的使用","uid":"1b1a4644b0bd397a00360966a4b49053","slug":"FMDB的使用","date":"2015-07-11T03:54:19.000Z","updated":"2020-03-11T13:35:08.000Z","comments":true,"path":"api/articles/FMDB的使用.json","cover":null,"text":"关于这篇Blog: 网上也有不少写FMDB用法的，我为什么还在这里重造轮子？有两个目的：1、自己做总结和备忘，在项目里会常用的东西2、 FMDB介绍：下载地址：https://github.com/ccgus/fmdb 如何集成1、如果你的工程使用了CocoaPods进行管理，直...","link":"","photos":[],"count_time":{"symbolsCount":"2.6k","symbolsTime":"2 mins."},"categories":[{"name":"iOS","slug":"iOS","count":36,"path":"api/categories/iOS.json"}],"tags":[{"name":"FMDB","slug":"FMDB","count":1,"path":"api/tags/FMDB.json"}],"author":{"name":"新风作浪","slug":"blog-author","avatar":"http://qiniu.niuxtech.cn/avatar.png","link":"/","description":"专注于你能控制的","socials":{"github":"https://github.com/duxinfeng","twitter":"https://twitter.com/iduxinfeng","stackoverflow":"","wechat":"","qq":"","weibo":"","zhihu":"","csdn":"https://blog.csdn.net/duxinfeng2010","juejin":"","customs":{}}}},{"title":"升级到Xcode6.4后插件失效解决办法","uid":"0686148ee45bcbbff09c1cfd7525d74f","slug":"升级到Xcode6-4后插件失效解决办法","date":"2015-07-08T05:53:02.000Z","updated":"2017-04-27T13:13:04.000Z","comments":true,"path":"api/articles/升级到Xcode6-4后插件失效解决办法.json","cover":null,"text":" 升级到Xcode 6.4 之后，插件失效不能使用， 1、首先要知道xcode的UUID,在终端下输入以下命令，会打开一个info.plist的文件，复制DVTPlugInCompatibilityUUID对应的值。 open /Applications/Xcode.app/Co...","link":"","photos":[],"count_time":{"symbolsCount":601,"symbolsTime":"1 mins."},"categories":[{"name":"iOS","slug":"iOS","count":36,"path":"api/categories/iOS.json"}],"tags":[{"name":"Xcode","slug":"Xcode","count":6,"path":"api/tags/Xcode.json"},{"name":"插件","slug":"插件","count":1,"path":"api/tags/插件.json"}],"author":{"name":"新风作浪","slug":"blog-author","avatar":"http://qiniu.niuxtech.cn/avatar.png","link":"/","description":"专注于你能控制的","socials":{"github":"https://github.com/duxinfeng","twitter":"https://twitter.com/iduxinfeng","stackoverflow":"","wechat":"","qq":"","weibo":"","zhihu":"","csdn":"https://blog.csdn.net/duxinfeng2010","juejin":"","customs":{}}}}]}