{"title":"根据ip获取省份/城市的接口","uid":"b5db695e23294ea81434ac131bd5db81","slug":"根据ip获取省份-城市的接口","date":"2015-10-12T06:47:44.000Z","updated":"2020-03-28T15:50:46.000Z","comments":true,"path":"api/articles/根据ip获取省份-城市的接口.json","keywords":null,"cover":null,"content":"<p>###淘宝接口</p>\n<p><a href=\"http://ip.taobao.com/service/getIpInfo.php?ip=119.57.173.141\">http://ip.taobao.com/service/getIpInfo.php?ip=119.57.173.141</a></p>\n<p>#####返回结果</p>\n<pre><code>&#123;\n&quot;code&quot;: 0,\n&quot;data&quot;: &#123;\n    &quot;country&quot;: &quot;中国&quot;,\n    &quot;country_id&quot;: &quot;CN&quot;,\n    &quot;area&quot;: &quot;华北&quot;,\n    &quot;area_id&quot;: &quot;100000&quot;,\n    &quot;region&quot;: &quot;北京市&quot;,\n    &quot;region_id&quot;: &quot;110000&quot;,\n    &quot;city&quot;: &quot;北京市&quot;,\n    &quot;city_id&quot;: &quot;110100&quot;,\n    &quot;county&quot;: &quot;&quot;,\n    &quot;county_id&quot;: &quot;-1&quot;,\n    &quot;isp&quot;: &quot;日升天信科技&quot;,\n    &quot;isp_id&quot;: &quot;1000157&quot;,\n    &quot;ip&quot;: &quot;119.57.173.141&quot;\n&#125;\n&#125;\n</code></pre>\n<p>###新浪接口</p>\n<p><a href=\"http://int.dpool.sina.com.cn/iplookup/iplookup.php?format=json&amp;ip=119.57.173.141\">http://int.dpool.sina.com.cn/iplookup/iplookup.php?format=json&amp;ip=119.57.173.141</a><br>#####返回结果</p>\n<pre><code>&#123;\n&quot;ret&quot;: 1,\n&quot;start&quot;: -1,\n&quot;end&quot;: -1,\n&quot;country&quot;: &quot;中国&quot;,\n&quot;province&quot;: &quot;北京&quot;,\n&quot;city&quot;: &quot;北京&quot;,\n&quot;district&quot;: &quot;&quot;,\n&quot;isp&quot;: &quot;&quot;,\n&quot;type&quot;: &quot;&quot;,\n&quot;desc&quot;: &quot;&quot;\n&#125;\n</code></pre>\n<p>###百度接口</p>\n<p><a href=\"http://api.map.baidu.com/location/ip\">http://api.map.baidu.com/location/ip</a></p>\n<p>需要申请key才能用<a href=\"http://developer.baidu.com/map/index.php?title=webapi/ip-api\">http://developer.baidu.com/map/index.php?title=webapi/ip-api</a></p>\n<p>#####返回结果</p>\n<pre><code>&#123;  \n    address: &quot;CN|北京|北京|None|CHINANET|1|None&quot;,   #地址  \n    content:       #详细内容  \n    &#123;  \n    address: &quot;北京市&quot;,   #简要地址  \n    address_detail:      #详细地址信息  \n    &#123;  \n    city: &quot;北京市&quot;,        #城市  \n    city_code: 131,       #百度城市代码  \n    district: &quot;&quot;,           #区县  \n    province: &quot;北京市&quot;,   #省份  \n    street: &quot;&quot;,            #街道  \n    street_number: &quot;&quot;    #门址  \n    &#125;,  \n    point:               #百度经纬度坐标值  \n    &#123;  \n    x: &quot;116.39564504&quot;,  \n    y: &quot;39.92998578&quot;  \n    &#125;  \n    &#125;,  \n    status: 0     #返回状态码  \n&#125;\n</code></pre>\n<p>###腾讯接口<br>如果网页端查看一下 直接<a href=\"http://ip.qq.com/\">http://ip.qq.com</a></p>\n<pre><code>欢迎您，尊敬的用户\n您当前的IP为：119.57.173.141\n该IP所在地为：中国北京市 联通\n</code></pre>\n","text":"###淘宝接口 http://ip.taobao.com/service/getIpInfo.php?ip=119.57.173.141 #####返回结果 &#123; &quot;code&quot;: 0, &quot;data&quot;: &#123; &quot;co...","link":"","photos":[],"count_time":{"symbolsCount":"2k","symbolsTime":"2 mins."},"categories":[{"name":"免费接口","slug":"免费接口","count":1,"path":"api/categories/免费接口.json"}],"tags":[{"name":"API","slug":"API","count":1,"path":"api/tags/API.json"},{"name":"城市","slug":"城市","count":1,"path":"api/tags/城市.json"}],"toc":"","author":{"name":"新风作浪","slug":"blog-author","avatar":"http://qiniu.niuxtech.cn/avatar.png","link":"/","description":"专注于你能控制的","socials":{"github":"https://github.com/duxinfeng","twitter":"https://twitter.com/iduxinfeng","stackoverflow":"","wechat":"","qq":"","weibo":"","zhihu":"","csdn":"https://blog.csdn.net/duxinfeng2010","juejin":"","customs":{}}},"mapped":true,"prev_post":{"title":"为何你会一年经验用十年","uid":"6b9bbfdd7365ff4aa18e16f1fcf485a9","slug":"为何你会一年经验用十年","date":"2015-10-18T08:13:53.000Z","updated":"2017-04-27T13:07:36.000Z","comments":true,"path":"api/articles/为何你会一年经验用十年.json","keywords":null,"cover":null,"text":"我在看个人Blog或者搜到一些个人Blog的时候对他们的关于比较感兴趣，然后就是他们的总结、反思、感悟等，我想知道他们在思考什么想什么，也想知道被人是如何介绍自己的。 在http://unclejoke.github.io/business.html 这篇文章里，博主讲讲到学习和...","link":"","photos":[],"count_time":{"symbolsCount":999,"symbolsTime":"1 mins."},"categories":[{"name":"生活","slug":"生活","count":13,"path":"api/categories/生活.json"}],"tags":[{"name":"总结","slug":"总结","count":1,"path":"api/tags/总结.json"}],"author":{"name":"新风作浪","slug":"blog-author","avatar":"http://qiniu.niuxtech.cn/avatar.png","link":"/","description":"专注于你能控制的","socials":{"github":"https://github.com/duxinfeng","twitter":"https://twitter.com/iduxinfeng","stackoverflow":"","wechat":"","qq":"","weibo":"","zhihu":"","csdn":"https://blog.csdn.net/duxinfeng2010","juejin":"","customs":{}}}},"next_post":{"title":"科学上网","uid":"e384082c21cec712db7f9620d92150dc","slug":"科学上网","date":"2015-10-08T05:59:57.000Z","updated":"2020-03-11T12:46:21.000Z","comments":true,"path":"api/articles/科学上网.json","keywords":null,"cover":null,"text":"本文不介绍如何翻越长城，只是个人爱好收集的一些免费方法，仅供折腾，不保证百分百成功。 2020.03.11 更新 http:&#x2F;&#x2F;www.googlen.org 2018.10.10 更新 以上方案全部失效，再放几个收藏的镜像网址.镜像只用于简单的搜索查询，请勿...","link":"","photos":[],"count_time":{"symbolsCount":"1.1k","symbolsTime":"1 mins."},"categories":[{"name":"工具","slug":"工具","count":10,"path":"api/categories/工具.json"}],"tags":[{"name":"Google","slug":"Google","count":1,"path":"api/tags/Google.json"}],"author":{"name":"新风作浪","slug":"blog-author","avatar":"http://qiniu.niuxtech.cn/avatar.png","link":"/","description":"专注于你能控制的","socials":{"github":"https://github.com/duxinfeng","twitter":"https://twitter.com/iduxinfeng","stackoverflow":"","wechat":"","qq":"","weibo":"","zhihu":"","csdn":"https://blog.csdn.net/duxinfeng2010","juejin":"","customs":{}}}}}